flask_value_checker/__init__.py
flask_value_checker/invigilator.py
flask_value_checker/value_checker.py
flask_value_checker/restrictions/__init__.py
flask_value_checker/restrictions/errors.py
flask_value_checker/restrictions/generic_restriction.py
flask_value_checker/restrictions/parsing.py
flask_value_checker/restrictions/restrictions.py
flask_value_checker-1.1.dist-info/LICENSE
flask_value_checker-1.1.dist-info/WHEEL
flask_value_checker-1.1.dist-info/METADATA
flask_value_checker-1.1.dist-info/RECORD
