Metadata-Version: 2.1
Name: flask-value-checker
Version: 1.1
Summary: lets check flask parameters
Home-page: https://github.com/therealadityashankar/flask-value-checker
License: UNKNOWN
Author: Aditya Shankar
Author-email: aditniru@gmail.com
Requires-Python: >=3.6,<4
Classifier: License :: OSI Approved :: MIT License
Classifier: Programming Language :: Python :: 3
Classifier: Intended Audience :: Developers
Classifier: Topic :: Software Development :: Libraries :: Python Modules
Requires-Dist: Flask>=1.1.1
Requires-Dist: colorama>=0.4.3
Requires-Dist: pytest >=5.3.4 ; extra == "test"
Provides-Extra: test
